transmissionrpc/__init__.py
transmissionrpc/client.py
transmissionrpc/constants.py
transmissionrpc/error.py
transmissionrpc/httphandler.py
transmissionrpc/session.py
transmissionrpc/torrent.py
transmissionrpc/utils.py
transmissionrpc_ng-0.14.0.dist-info/LICENSE
transmissionrpc_ng-0.14.0.dist-info/METADATA
transmissionrpc_ng-0.14.0.dist-info/WHEEL
transmissionrpc_ng-0.14.0.dist-info/top_level.txt
transmissionrpc_ng-0.14.0.dist-info/zip-safe
transmissionrpc_ng-0.14.0.dist-info/RECORD
