Metadata-Version: 2.1
Name: transmissionrpc-ng
Version: 0.14.0
Summary: Python module that implements the Transmission BitTorent client RPC protocol.
Home-page: https://github.com/0x022b/transmissionrpc-ng
Author: Janne K
Author-email: 0x022b@gmail.com
License: UNKNOWN
Keywords: transmission bittorent torrent
Platform: UNKNOWN
Classifier: Intended Audience :: Developers
Classifier: License :: OSI Approved :: MIT License
Classifier: Topic :: Communications :: File Sharing
Classifier: Topic :: Internet
Requires-Python: >=3.6
